sorting_api/__init__.py
sorting_api/__main__.py
sorting_api/main.py
sorting_api/routing/__init__.py
sorting_api/routing/router.py
sorting_api/routing/endpoints/__init__.py
sorting_api/routing/endpoints/random.py
sorting_api/routing/endpoints/sort.py
sorting_api/static/__init__.py
sorting_api/static/sorting_algo.py
sorting_api/utils/__init__.py
sorting_api/utils/body_validation.py
Sorting_API-1.0.1.dist-info/METADATA
Sorting_API-1.0.1.dist-info/WHEEL
Sorting_API-1.0.1.dist-info/entry_points.txt
Sorting_API-1.0.1.dist-info/top_level.txt
Sorting_API-1.0.1.dist-info/RECORD
