Metadata-Version: 2.1
Name: Sorting-API
Version: 1.0.1
Author: Andrea Broccoletti, Simone Lesinigo
Requires-Dist: uvicorn
Requires-Dist: fastapi
Requires-Dist: pysort
